{
    "status": "done",
    "recipe": [
        [
            {
                "type": "ingredient",
                "value": "塩"
            },
            {
                "type": "particle",
                "value": "を"
            },
            {
                "type": "operation",
                "value": "むく"
            }
        ],
        [
            {
                "type": "ingredient",
                "value": "オリーブオイル"
            },
            {
                "type": "particle",
                "value": "を"
            },
            {
                "type": "operation",
                "value": "割る"
            }
        ],
        [
            {
                "type": "ingredient",
                "value": "マヨネーズ"
            },
            {
                "type": "particle",
                "value": "を"
            },
            {
                "type": "ingredient",
                "value": "油"
            },
            {
                "type": "particle",
                "value": "で"
            },
            {
                "type": "operation",
                "value": "包む"
            }
        ],
        [
            {
                "type": "ingredient",
                "value": "ビーフジャーキー"
            },
            {
                "type": "particle",
                "value": "から"
            },
            {
                "type": "ingredient",
                "value": "えび"
            },
            {
                "type": "particle",
                "value": "を"
            },
            {
                "type": "operation",
                "value": "むく"
            }
        ]
    ],
    "job_id": "ecbff513-c7ab-4050-b5b9-e451628b1462",
    "created_at": "2025-09-07T06:03:25.218852",
    "estimated_duration": 53667,
    "started_at": "2025-09-07T06:03:25.221131",
    "title": "オイル包みのソルトシュリンプ",
    "comment": "見た目のインパクトが強く、食感のコントラストを楽しめる冒険的な一品です。塩や油の扱い方が独特なので、塩分と油分のバランスには気を付けてください。奇抜な組み合わせですが、思い切って試せば話題になること間違いなしです。",
    "image_prompt": "薄く裂いたビーフジャーキーの間からぷりっとした海老が顔を覗かせ、周囲にはオリーブオイルの光沢のある薄い膜で包まれたクリーミーなマヨネーズがそっと置かれている。フレーク状に“むかれた”塩がアクセントとして散らされ、オイルの金色の反射が全体を艶やかに演出。木のプレートに盛り付け、ルッコラやレモンのくし切りを添え、温かい自然光が素材の質感を引き立てる。浅い被写界深度でクローズアップし、海老の弾力やマヨネーズの滑らかさ、ビーフジャーキーの繊維感をディテール豊かに描写。色調は温かくコントラスト高めで、現実的かつ食欲をそそる画面に仕上げてください。",
    "finished_at": "2025-09-07T06:04:11.226513"
}