{
    "status": "done",
    "recipe": [
        [
            {
                "type": "ingredient",
                "value": "さつまいも"
            },
            {
                "type": "particle",
                "value": "に"
            },
            {
                "type": "ingredient",
                "value": "砂糖"
            },
            {
                "type": "particle",
                "value": "を"
            },
            {
                "type": "operation",
                "value": "かける"
            },
            {
                "type": "operation",
                "value": "焼く"
            }
        ]
    ],
    "job_id": "bedb0d1f-0aad-45fb-910b-d30374bc430d",
    "created_at": "2025-09-07T05:54:52.210855",
    "estimated_duration": 55480,
    "started_at": "2025-09-07T05:54:52.212905",
    "title": "砂糖焼きさつまいも",
    "comment": "砂糖だけで焼くシンプルさが、さつまいもの自然な甘みをぐっと引き出してくれます。表面のキャラメリゼと中のホクホク感の対比が食欲をそそる一品です。砂糖は焦げやすいので焼き時間に注意を、焦げても「焦げ目のアクセント」と言い張れば場が和むかもしれません。",
    "image_prompt": "皮ごと丁寧に焼かれたさつまいもが、表面にまぶした砂糖が溶けてキャラメル状に艶を帯びている完成イメージ。半分に割られて断面は鮮やかなオレンジ色で、湯気がほんのり立ち上り、ホクホクの繊維がやわらかく見える。皮には薄い焦げ目とカリッとした質感があり、溶けた砂糖がとろりと垂れ、ところどころに光る結晶の跡が残る。木製のまな板か素朴な陶器の皿に載せ、暖色の自然光で温かさを強調。背景はぼかして料理に視線が集中するようにし、シンプルで素材の良さだけで勝負した砂糖のみの調理であることが伝わる細部描写を盛り込んでください。",
    "finished_at": "2025-09-07T05:55:45.084557"
}