{
    "status": "done",
    "recipe": [
        [
            {
                "type": "ingredient",
                "value": "そうめん"
            },
            {
                "type": "ingredient",
                "value": "トマト"
            },
            {
                "type": "operation",
                "value": "切る"
            }
        ]
    ],
    "job_id": "071edf8d-d414-443f-9c68-7e1694c4ab6c",
    "created_at": "2025-09-07T04:18:23.585282",
    "estimated_duration": 45867,
    "started_at": "2025-09-07T04:18:23.587106",
    "title": "トマトそうめん",
    "comment": "とてもシンプルで夏にぴったり、トマトの瑞々しさとそうめんのつるっとした食感が楽しい一品です。めんつゆやオリーブオイル、塩で軽く味を整えるとさらに美味しくなります。トマトを切るときは滑りやすいので包丁と指の扱いに注意してください。",
    "image_prompt": "冷たくしめた白く細いそうめんが深めの器に美しく巻かれ、その上に瑞々しい真っ赤なトマトの薄切りと角切りがたっぷりと盛られている様子。トマトの滴が麺にほんのり染み込み、オリーブオイルの光る膜と刻み青ねぎ、白ごまがアクセントになり、レモンの薄切りや氷片がそっと添えられている。木のテーブルの上に置かれ、自然光が当たって器の外側にうっすらと結露が生まれ、涼しげで食欲をそそる夏の一皿をクローズアップで捉えた構図。背景は柔らかくボケて箸置きと箸が控えめに見え、全体に温かみのある色調で美味しさと清涼感を強調している。",
    "finished_at": "2025-09-07T04:19:07.082526"
}