{
    "status": "done",
    "recipe": [
        [
            {
                "type": "ingredient",
                "value": "ごはん"
            },
            {
                "type": "ingredient",
                "value": "ケチャップ"
            },
            {
                "type": "ingredient",
                "value": "鶏肉"
            },
            {
                "type": "ingredient",
                "value": "たまねぎ"
            },
            {
                "type": "particle",
                "value": "を"
            },
            {
                "type": "operation",
                "value": "炒める"
            },
            {
                "type": "particle",
                "value": "で"
            },
            {
                "type": "ingredient",
                "value": "たまご"
            },
            {
                "type": "particle",
                "value": "を"
            },
            {
                "type": "operation",
                "value": "焼く"
            },
            {
                "type": "particle",
                "value": "で"
            },
            {
                "type": "operation",
                "value": "のせる"
            }
        ]
    ],
    "job_id": "a27a3a2e-4cde-41d0-98ac-32a0618b69c2",
    "created_at": "2025-09-07T01:23:13.415852",
    "estimated_duration": 48921,
    "started_at": "2025-09-07T01:23:13.417905",
    "title": "チキンケチャップライス 目玉焼きのせ",
    "comment": "ケチャップの甘酸っぱさが鶏肉と玉ねぎの旨味を引き立て、手早く作れて満足感の高い一品です。目玉焼きをのせることで見た目も豪華になり、黄身を割ればソースのようにライス全体に絡んでさらに美味しくなります。家庭で気負わず作れるのに、食卓ではしっかり「今日のヒーロー」になれる一皿です。",
    "image_prompt": "熱々のケチャップライスが皿の中央に山盛りになり、鶏肉の一口大の刻みがほどよく混ざり、飴色に炒めた玉ねぎがところどころ見える。ケチャップの赤い光沢が米粒に絡み、ところどころ香ばしい焦げ目が付いている。上には薄く焼かれた白身と、とろりとした黄金色の半熟の黄身がのり、黄身が軽く潰れてライスにかかり始めている様子。刻んだパセリと黒胡椒が彩りを添え、皿の端にバターの溶けた艶やかな跡が見える。木目のテーブル、柔らかな朝の逆光、浅い被写界深度で背景をぼかしたクローズアップ、温かく家庭的で食欲をそそる雰囲気を強調して描写してください。",
    "finished_at": "2025-09-07T01:23:52.069516"
}