{
    "status": "done",
    "recipe": [
        [
            {
                "type": "ingredient",
                "value": "しそ"
            },
            {
                "type": "particle",
                "value": "と"
            },
            {
                "type": "ingredient",
                "value": "なし"
            },
            {
                "type": "particle",
                "value": "と"
            },
            {
                "type": "ingredient",
                "value": "もも"
            },
            {
                "type": "particle",
                "value": "と"
            },
            {
                "type": "ingredient",
                "value": "メロン"
            },
            {
                "type": "particle",
                "value": "で"
            },
            {
                "type": "operation",
                "value": "和える"
            },
            {
                "type": "ingredient",
                "value": "パイナップル"
            },
            {
                "type": "particle",
                "value": "に"
            },
            {
                "type": "operation",
                "value": "盛る"
            }
        ]
    ],
    "job_id": "842d1515-df4d-4f0e-89c3-7a9f78e4ee71",
    "created_at": "2025-09-07T01:31:16.644519",
    "estimated_duration": 47212,
    "started_at": "2025-09-07T01:31:16.646616",
    "title": "しそ香るフルーツパイナップルボート",
    "comment": "しその爽やかな香りが梨・桃・メロンの甘みをきゅっと引き締める、和と南国の楽しい出会いです。パイナップルを器にすることで見た目の遊び心とボリューム感が出て、パーティーでも注目の一品になります。盛り付けはパイナップルの芯をしっかり取り除くのと、しその量を好みで調整するのがポイント、意外とさっぱり何個でも食べられます！",
    "image_prompt": "ハーフに切ったパイナップルの殻を器にして盛り付けた、彩り豊かなフルーツサラダのクローズアップ。瑞々しい梨の角切り、薄くスライスした桃、メロンの一口大の果肉が混ざり合い、鮮やかな緑の刻みしそが上からふんわり散らされている。パイナップルの黄金色の縁が光り、果汁のつやと小さなしずくが表面にきらめく様子を写す。木目のトレイにのせた南国風のテーブルセッティングで、柔らかい自然光の逆光が果実の透明感を引き立て、浅い被写界深度で背景を大きくぼかした高解像度のフードフォトを想定。色彩は鮮やかにコントラストを効かせ、テクスチャー（ジューシーな果肉、葉の繊維感、パイナップルのざらつき）を強調して見る人の食欲をそそるように描写する。",
    "finished_at": "2025-09-07T01:31:59.037667"
}